marsis/__init__.py
marsis/campbell.py
marsis/edr.py
marsis/fetch.py
marsis/mcmichael.py
marsis/output.py
marsis/parsetab.py
marsis/plain.py
marsis/util.py
marsis-0.0.8.data/scripts/marsis_download.py
marsis-0.0.8.data/scripts/marsis_processor.py
marsis-0.0.8.dist-info/LICENSE
marsis-0.0.8.dist-info/METADATA
marsis-0.0.8.dist-info/WHEEL
marsis-0.0.8.dist-info/top_level.txt
marsis-0.0.8.dist-info/RECORD
