Metadata-Version: 2.1
Name: marsis
Version: 0.0.8
Summary: An open source processor for the MARSIS instrument on Mars Express
Home-page: https://github.com/mchristoffersen/marsis_processor
Author: Michael Christoffersen
Author-email: mchristo28@gmail.com
Project-URL: Bug Tracker, https://github.com/mchristoffersen/marsis_processor/issues
Classifier: Programming Language :: Python :: 3
Classifier: License :: OSI Approved :: MIT License
Classifier: Operating System :: POSIX :: Linux
Requires-Python: >=3.6
License-File: LICENSE
Requires-Dist: pandas
Requires-Dist: numpy
Requires-Dist: matplotlib
Requires-Dist: rasterio
Requires-Dist: ply
Requires-Dist: pyproj
Requires-Dist: tqdm
Requires-Dist: scipy
Requires-Dist: Pillow
